{"module_name":"v.profile","contents":[{"attributes":{},"comments":[],"children":[],"tags":[],"file_path":"D:\\Games\\Proekti\\V\\v\\vlib\\v\\profile\\api.v","content":"fn state() bool","name":"state","parent_name":"","return_type":"bool","pos":{"len":19,"line_nr":5,"pos":67,"col":0,"last_line":7},"platform":"cross","kind":"function","public":true,"from_scope":false},{"attributes":{},"comments":[],"children":[],"tags":[],"file_path":"D:\\Games\\Proekti\\V\\v\\vlib\\v\\profile\\api.v","content":"fn on(state bool)","name":"on","parent_name":"","return_type":"void","pos":{"len":21,"line_nr":10,"pos":133,"col":0,"last_line":12},"platform":"cross","kind":"function","public":true,"from_scope":false}],"generator":"vdoc","time_generated":"2024-02-05 19:45:43"}