{"module_name":"x","description":"## Description:\n\n`x` is not a module by itself, but a namespace for other modules. The modules here are considered experimental/subject to change.\n\nIn time, `x` modules will either become ordinary vlib modules, or they will be split to their own repositories, and distributed apart from V.","contents":[{"attributes":{},"comments":[],"children":[{"attributes":{},"comments":[],"children":[],"tags":[],"file_path":"D:\\Games\\Proekti\\V\\v\\vlib\\x\\x.v","content":"const description = 'an empty module, used as a placeholder, for other modules'","name":"","parent_name":"","return_type":"","pos":{"len":9,"line_nr":2,"pos":10,"col":0,"last_line":2},"platform":"cross","kind":"const_group","public":true,"from_scope":false}],"tags":[],"file_path":"","content":"","name":"Constants","parent_name":"","return_type":"","pos":{"len":0,"line_nr":0,"pos":0,"col":0,"last_line":0},"platform":"auto","kind":"const_group","public":false,"from_scope":false}],"generator":"vdoc","time_generated":"2024-01-13 21:06:44"}